ape_apeman/__init__.py
ape_apeman/account.py
ape_apeman/cli.py
ape_apeman/contract.py
ape_apeman/exception_handler.py
ape_apeman/exceptions.py
ape_apeman/factory.py
ape_apeman/json.py
ape_apeman/manager.py
ape_apeman/version.py
ape_apeman-1.0.1.dist-info/entry_points.txt
ape_apeman-1.0.1.dist-info/LICENSE
ape_apeman-1.0.1.dist-info/WHEEL
ape_apeman-1.0.1.dist-info/METADATA
ape_apeman-1.0.1.dist-info/RECORD
