Metadata-Version: 2.1
Name: ape-apeman
Version: 1.0.1
Summary: Top-level package for ape-apeman.
Keywords: ape apeman eth-ape
Author-email: Matt Krueger <mkrueger@rstms.net>
Classifier: Intended Audience :: Developers
Classifier: Natural Language :: English
Classifier: Programming Language :: Python :: 3
Classifier: Programming Language :: Python :: 3.10
Requires-Dist: ape-alchemy==0.6.0
Requires-Dist: ape-etherscan==0.6.0
Requires-Dist: click==8.1.3
Requires-Dist: eth-ape==0.6.5
Requires-Dist: ape-hardhat==0.6.0
Requires-Dist: python-box
Requires-Dist: black ; extra == "dev"
Requires-Dist: bump2version ; extra == "dev"
Requires-Dist: coverage ; extra == "dev"
Requires-Dist: isort ; extra == "dev"
Requires-Dist: flake8 ; extra == "dev"
Requires-Dist: flake8-length ; extra == "dev"
Requires-Dist: pytest ; extra == "dev"
Requires-Dist: pytest-datadir ; extra == "dev"
Requires-Dist: pdbpp ; extra == "dev"
Requires-Dist: m2r2 ; extra == "docs"
Requires-Dist: sphinx ; extra == "docs"
Requires-Dist: sphinx-click ; extra == "docs"
Requires-Dist: sphinx-rtd-theme ; extra == "docs"
Project-URL: Home, https://github.com/rstms/ape_apeman
Provides-Extra: dev
Provides-Extra: docs
